sailsim/__init__.py
sailsim/main.py
sailsim/boat/Boat.py
sailsim/boat/BoatDataHolder.py
sailsim/boat/__init__.py
sailsim/boat/boat_forces.py
sailsim/boat/boat_torques.py
sailsim/boat/boatgetset.py
sailsim/boat/coefficientsapprox.py
sailsim/gui/ConfigBoat.py
sailsim/gui/ConfigWind.py
sailsim/gui/SailsimGUI.py
sailsim/gui/__init__.py
sailsim/gui/actionslots.py
sailsim/gui/boatInspector.py
sailsim/gui/mapView.py
sailsim/gui/qtmain.py
sailsim/gui/tkinterutils.py
sailsim/gui/valueInspector.py
sailsim/sailor/Commands.py
sailsim/sailor/Sailor.py
sailsim/sailor/__init__.py
sailsim/sailor/sailorgetset.py
sailsim/simulation/Frame.py
sailsim/simulation/FrameList.py
sailsim/simulation/Simulation.py
sailsim/simulation/__init__.py
sailsim/utils/__init__.py
sailsim/utils/anglecalculations.py
sailsim/utils/constants.py
sailsim/utils/conversion.py
sailsim/utils/coordconversion.py
sailsim/wind/Fluctuationfield.py
sailsim/wind/Squall.py
sailsim/wind/Squallfield.py
sailsim/wind/Wind.py
sailsim/wind/Windfield.py
sailsim/wind/__init__.py
sailsim/world/World.py
sailsim/world/__init__.py
tests/__init__.py
tests/basictest.py
tests/benchmark.py
tests/boat/__init__.py
tests/gui/__init__.py
tests/gui/_test_SailsimGUI.py
tests/sailor/__init__.py
tests/simulation/__init__.py
tests/simulation/test_Simulation.py
tests/utils/__init__.py
tests/utils/test_anglecalculations.py
tests/utils/test_coordconversion.py
tests/world/__init__.py
sailsim-0.0.2.dist-info/LICENSE
sailsim-0.0.2.dist-info/METADATA
sailsim-0.0.2.dist-info/WHEEL
sailsim-0.0.2.dist-info/top_level.txt
sailsim-0.0.2.dist-info/RECORD
