Metadata-Version: 2.1
Name: sailsim
Version: 0.0.2
Summary: A program to simulate sailboats and test sailing algorithms.
Home-page: https://github.com/mfbehrens99/sailsim
Author: Tillman Keller & Michael Behrens
Author-email: mfbehrens99@gmail.com
License: UNKNOWN
Platform: UNKNOWN
Classifier: Development Status :: 3 - Alpha
Classifier: Intended Audience :: Education
Classifier: Intended Audience :: Science/Research
Classifier: Topic :: Scientific/Engineering
Requires-Python: >=3
Requires-Dist: opensimplex
Requires-Dist: PySide6
